{
  "rss_info": [
    {
      "title": "羊毛日报",
      "url": "https://ym.today/feed"
    },
    {
      "title": "反斗限免",
      "url": "http://free.apprcn.com/feed/"
    },
    {
      "title": "限时免费",
      "url": "https://xianshiyouhui.com"
    },
    {
      "title": "ahhhhfs",
      "url": "https://www.ahhhhfs.com/feed.xml"
    },    
    {
      "title": "Mareep",
      "url": "https://blog.mareep.net/atom.xml"
    },       
    {
      "title": "五月天微博",
      "url": "https://rsshub.app/weibo/user/3365597502"
    }
  ]
}